microsoft_teams_mcp/__init__.py
microsoft_teams_mcp/server.py
microsoft_teams_mcp-1.1.7.dist-info/licenses/LICENSE
microsoft_teams_mcp-1.1.7.dist-info/METADATA
microsoft_teams_mcp-1.1.7.dist-info/WHEEL
microsoft_teams_mcp-1.1.7.dist-info/entry_points.txt
microsoft_teams_mcp-1.1.7.dist-info/top_level.txt
microsoft_teams_mcp-1.1.7.dist-info/RECORD
