Metadata-Version: 2.4
Name: microsoft-teams-mcp
Version: 1.1.7
Summary: Microsoft Teams meeting scheduler MCP tool using Microsoft Graph API
Home-page: https://github.com/alivnavc/Microsoft-Teams-Meetings-MCP-Server
Author: Naveen Chowdary Aliveli
Author-email: naveenchowdary5175@gmail.com
Classifier: Programming Language :: Python :: 3
Classifier: License :: OSI Approved :: MIT License
Classifier: Operating System :: OS Independent
Requires-Python: >=3.9
License-File: LICENSE
Requires-Dist: fastmcp==2.11.2
Requires-Dist: requests==2.32.4
Requires-Dist: httpx==0.28.1
Requires-Dist: python-dateutil==2.9.0.post0
Requires-Dist: pytz==2025.2
Requires-Dist: msgraph-core==1.3.5
Requires-Dist: azure-identity==1.24.0
Requires-Dist: python-dotenv==1.1.1
Requires-Dist: msgraph-sdk==1.40.0
Dynamic: author
Dynamic: author-email
Dynamic: classifier
Dynamic: home-page
Dynamic: license-file
Dynamic: requires-dist
Dynamic: requires-python
Dynamic: summary
